FanchenHuashu/README.md
FanchenHuashu/__init__.py
FanchenHuashu/__main__.py
FanchenHuashu/file.epub
FanchenHuashu/index.html
FanchenHuashu/css/__init__.py
FanchenHuashu/css/annotations.css
FanchenHuashu/css/main.css
FanchenHuashu/css/normalize.css
FanchenHuashu/css/popup.css
FanchenHuashu/font/__init__.py
FanchenHuashu/font/fontello.eot
FanchenHuashu/font/fontello.svg
FanchenHuashu/font/fontello.ttf
FanchenHuashu/font/fontello.woff
FanchenHuashu/img/__init__.py
FanchenHuashu/img/annotator-glyph-sprite.png
FanchenHuashu/img/annotator-icon-sprite.png
FanchenHuashu/img/apple-touch-icon.png
FanchenHuashu/img/cancelfullscreen.png
FanchenHuashu/img/close.png
FanchenHuashu/img/fullscreen.png
FanchenHuashu/img/loader.gif
FanchenHuashu/img/menu-icon.png
FanchenHuashu/img/save.png
FanchenHuashu/img/saved.png
FanchenHuashu/img/settings-s.png
FanchenHuashu/img/settings.png
FanchenHuashu/img/star.png
FanchenHuashu/js/__init__.py
FanchenHuashu/js/epub.js
FanchenHuashu/js/epub.min.js
FanchenHuashu/js/epub.min.map
FanchenHuashu/js/hooks.min.js
FanchenHuashu/js/hooks.min.map
FanchenHuashu/js/reader.js
FanchenHuashu/js/reader.js.map
FanchenHuashu/js/reader.min.js
FanchenHuashu/js/reader.min.map
FanchenHuashu/js/hooks/__init__.py
FanchenHuashu/js/hooks/extensions/__init__.py
FanchenHuashu/js/hooks/extensions/highlight.js
FanchenHuashu/js/libs/__init__.py
FanchenHuashu/js/libs/jquery.min.js
FanchenHuashu/js/libs/localforage.min.js
FanchenHuashu/js/libs/screenfull.js
FanchenHuashu/js/libs/screenfull.min.js
FanchenHuashu/js/libs/zip.min.js
FanchenHuashu/js/plugins/__init__.py
FanchenHuashu/js/plugins/hypothesis.js
FanchenHuashu/js/plugins/search.js
fanchen_huashu-2022.10.11.0.dist-info/METADATA
fanchen_huashu-2022.10.11.0.dist-info/WHEEL
fanchen_huashu-2022.10.11.0.dist-info/entry_points.txt
fanchen_huashu-2022.10.11.0.dist-info/top_level.txt
fanchen_huashu-2022.10.11.0.dist-info/RECORD
